datastore_client/__init__.py
datastore_client/datastore_pb2.py
datastore_client/datastore_pb2_twirp.py
decode_datastore_client-0.2.0.dist-info/LICENSE
decode_datastore_client-0.2.0.dist-info/METADATA
decode_datastore_client-0.2.0.dist-info/WHEEL
decode_datastore_client-0.2.0.dist-info/top_level.txt
decode_datastore_client-0.2.0.dist-info/RECORD
