Metadata-Version: 2.1
Name: decode-datastore-client
Version: 0.2.0
Summary: Python client for the DECODE encrypted datastore
Home-page: https://github.com/thingful/decode-datastore-client-py
Maintainer: Sam Mulube
Maintainer-email: sam@thingful.net
License: UNKNOWN
Platform: UNKNOWN
Classifier: Development Status :: 3 - Alpha
Classifier: License :: OSI Approved :: Apache Software License
Classifier: Operating System :: OS Independent
Classifier: Programming Language :: Python
Requires-Dist: protobuf
